imf_data_mcp/__init__.py
imf_data_mcp/utils.py
mseep_imf_data_mcp-0.1.4.dist-info/licenses/LICENSE
mseep_imf_data_mcp-0.1.4.dist-info/METADATA
mseep_imf_data_mcp-0.1.4.dist-info/WHEEL
mseep_imf_data_mcp-0.1.4.dist-info/entry_points.txt
mseep_imf_data_mcp-0.1.4.dist-info/top_level.txt
mseep_imf_data_mcp-0.1.4.dist-info/RECORD
